pynetsys/__init__.py
pynetsys/_packet.py
pynetsys/_tool.py
pynetsys/constants.py
pynetsys/error.py
pynetsys-0.1.6.dist-info/LICENSE
pynetsys-0.1.6.dist-info/METADATA
pynetsys-0.1.6.dist-info/WHEEL
pynetsys-0.1.6.dist-info/top_level.txt
pynetsys-0.1.6.dist-info/RECORD
